readonlystorage/__init__.py
tests/__init__.py
tests/test_readonly_storage.py
readonlystorage-0.0.1.dist-info/LICENSE
readonlystorage-0.0.1.dist-info/METADATA
readonlystorage-0.0.1.dist-info/WHEEL
readonlystorage-0.0.1.dist-info/top_level.txt
readonlystorage-0.0.1.dist-info/RECORD
