Metadata-Version: 2.1
Name: readonlystorage
Version: 0.0.1
Summary: A readonly wrapper around a ZODB storage
Home-page: https://gitlab.com/yaal/readonlystorage
Author: Yaal
Author-email: contact@yaal.fr
License: UNKNOWN
Platform: UNKNOWN
Classifier: Programming Language :: Python :: 2
Classifier: Programming Language :: Python :: 3
Classifier: License :: OSI Approved :: MIT License
Classifier: Operating System :: OS Independent
Requires-Dist: ZODB
